pil/__init__.py
pil/all.py
pil/audio.py
pil/images.py
pil/video.py
test/__init__.py
test/all.py
test/audio.py
test/compiler.py
test/evaluator.py
test/example.py
test/example2.py
test/f_and_f.py
test/f_and_f2.py
test/first_follow.py
test/images.py
test/lang.py
test/main.py
test/new_one.py
test/solution.py
test/test.py
test/test2.py
test/video.py
test/x.py
test/xy.py
pil_python_pillow-0.1.6.dist-info/METADATA
pil_python_pillow-0.1.6.dist-info/WHEEL
pil_python_pillow-0.1.6.dist-info/top_level.txt
pil_python_pillow-0.1.6.dist-info/RECORD
